{
  "data": [
    {
      "id": "dp3-1",
      "name": "ampharos"
    },
    {
      "id": "ex12-1",
      "name": "aerodactyl"
    },
    {
      "id": "mcd19-1",
      "name": "caterpie"
    },
    {
      "id": "ex7-1",
      "name": "azumarill"
    },
    {
      "id": "sm9-1",
      "name": "celebi & venusaur-gx"
    },
    {
      "id": "pl1-2",
      "name": "blastoise"
    },
    {
      "id": "ex3-2",
      "name": "altaria"
    },
    {
      "id": "sm9-2",
      "name": "weedle"
    },
    {
      "id": "mcd19-2",
      "name": "alolan exeggutor"
    },
    {
      "id": "xy5-2",
      "name": "kakuna"
    },
    {
      "id": "sm12-1",
      "name": "venusaur & snivy-gx"
    },
    {
      "id": "si1-1",
      "name": "mew"
    },
    {
      "id": "sm3-1",
      "name": "caterpie"
    },
    {
      "id": "pop7-1",
      "name": "ampharos"
    },
    {
      "id": "bw1-2",
      "name": "snivy"
    },
    {
      "id": "base4-3",
      "name": "chansey"
    },
    {
      "id": "hgss4-3",
      "name": "celebi"
    },
    {
      "id": "ex7-3",
      "name": "dark crobat"
    },
    {
      "id": "swsh35-2",
      "name": "weedle"
    },
    {
      "id": "xy2-3",
      "name": "butterfree"
    },
    {
      "id": "sm9-3",
      "name": "weedle"
    },
    {
      "id": "sm1-2",
      "name": "metapod"
    },
    {
      "id": "mcd19-3",
      "name": "magmar"
    },
    {
      "id": "dp3-3",
      "name": "charizard"
    },
    {
      "id": "base1-1",
      "name": "alakazam"
    },
    {
      "id": "ex8-1",
      "name": "altaria"
    },
    {
      "id": "pop5-1",
      "name": "ho-oh"
    },
    {
      "id": "xy10-1",
      "name": "shuckle"
    },
    {
      "id": "ecard2-h1",
      "name": "ampharos"
    },
    {
      "id": "base4-1",
      "name": "alakazam"
    },
    {
      "id": "ex11-1",
      "name": "beedrill δ"
    },
    {
      "id": "base3-2",
      "name": "articuno"
    },
    {
      "id": "gym1-2",
      "name": "brock's rhydon"
    },
    {
      "id": "ex14-1",
      "name": "banette"
    },
    {
      "id": "sm115-1",
      "name": "caterpie"
    },
    {
      "id": "col1-1",
      "name": "clefable"
    },
    {
      "id": "ex9-1",
      "name": "blaziken"
    },
    {
      "id": "bw10-1",
      "name": "surskit"
    },
    {
      "id": "ex9-2",
      "name": "deoxys"
    },
    {
      "id": "ru1-3",
      "name": "ninetales"
    },
    {
      "id": "xy5-3",
      "name": "beedrill"
    },
    {
      "id": "pl3-3",
      "name": "drifblim fb"
    },
    {
      "id": "xy7-2",
      "name": "gloom"
    },
    {
      "id": "bw10-2",
      "name": "masquerain"
    },
    {
      "id": "ex12-3",
      "name": "cradily"
    },
    {
      "id": "xy11-2",
      "name": "tangrowth"
    },
    {
      "id": "ex3-3",
      "name": "crawdaunt"
    },
    {
      "id": "dv1-3",
      "name": "dragonair"
    },
    {
      "id": "xy4-1",
      "name": "venonat"
    },
    {
      "id": "bw4-1",
      "name": "pinsir"
    },
    {
      "id": "bw7-1",
      "name": "oddish"
    },
    {
      "id": "sm5-1",
      "name": "exeggcute"
    },
    {
      "id": "sm8-1",
      "name": "tangela"
    },
    {
      "id": "hgss4-1",
      "name": "aggron"
    },
    {
      "id": "xy5-1",
      "name": "weedle"
    },
    {
      "id": "pl1-1",
      "name": "ampharos"
    },
    {
      "id": "det1-1",
      "name": "bulbasaur"
    },
    {
      "id": "dv1-1",
      "name": "dratini"
    },
    {
      "id": "pl3-1",
      "name": "absol g"
    },
    {
      "id": "xy2-1",
      "name": "caterpie"
    },
    {
      "id": "pop6-1",
      "name": "bastiodon"
    },
    {
      "id": "ecard2-h2",
      "name": "arcanine"
    },
    {
      "id": "hgss4-2",
      "name": "altaria"
    },
    {
      "id": "pl3-2",
      "name": "blaziken fb"
    },
    {
      "id": "ex11-2",
      "name": "crobat δ"
    },
    {
      "id": "pop6-2",
      "name": "lucario"
    },
    {
      "id": "base4-2",
      "name": "blastoise"
    },
    {
      "id": "ex12-2",
      "name": "aggron"
    },
    {
      "id": "ex7-2",
      "name": "dark ampharos"
    },
    {
      "id": "xy11-1",
      "name": "tangela"
    },
    {
      "id": "bw1-1",
      "name": "snivy"
    },
    {
      "id": "gym2-1",
      "name": "blaine's arcanine"
    },
    {
      "id": "swsh35-1",
      "name": "venusaur v"
    },
    {
      "id": "sm1-1",
      "name": "caterpie"
    },
    {
      "id": "ex13-1",
      "name": "armaldo δ"
    },
    {
      "id": "pop6-3",
      "name": "manaphy"
    },
    {
      "id": "ex11-3",
      "name": "dragonite δ"
    },
    {
      "id": "ex13-2",
      "name": "cradily δ"
    },
    {
      "id": "gym2-2",
      "name": "blaine's charizard"
    },
    {
      "id": "det1-3",
      "name": "morelull"
    },
    {
      "id": "pop7-2",
      "name": "gallade"
    },
    {
      "id": "col1-2",
      "name": "deoxys"
    },
    {
      "id": "pl1-3",
      "name": "blaziken"
    },
    {
      "id": "sm115-2",
      "name": "metapod"
    },
    {
      "id": "sm2-1",
      "name": "bellsprout"
    },
    {
      "id": "ex4-1",
      "name": "team aqua's cacturne"
    },
    {
      "id": "bw9-1",
      "name": "weedle"
    },
    {
      "id": "ex3-1",
      "name": "absol"
    },
    {
      "id": "ru1-1",
      "name": "venusaur"
    },
    {
      "id": "hgss1-1",
      "name": "arcanine"
    },
    {
      "id": "gym1-1",
      "name": "blaine's moltres"
    },
    {
      "id": "base3-1",
      "name": "aerodactyl"
    },
    {
      "id": "dp3-2",
      "name": "blastoise"
    },
    {
      "id": "xy2-2",
      "name": "metapod"
    },
    {
      "id": "hgss1-2",
      "name": "azumarill"
    },
    {
      "id": "det1-2",
      "name": "ludicolo"
    },
    {
      "id": "ru1-2",
      "name": "cherrim"
    },
    {
      "id": "dp1-1",
      "name": "dialga"
    },
    {
      "id": "xy7-1",
      "name": "oddish"
    },
    {
      "id": "dv1-2",
      "name": "dratini"
    },
    {
      "id": "ecard2-h3",
      "name": "ariados"
    },
    {
      "id": "sm12-2",
      "name": "oddish"
    },
    {
      "id": "si1-2",
      "name": "pidgeot"
    },
    {
      "id": "base3-3",
      "name": "ditto"
    },
    {
      "id": "hgss1-3",
      "name": "clefable"
    },
    {
      "id": "gym1-3",
      "name": "erika's clefable"
    },
    {
      "id": "base5-1",
      "name": "dark alakazam"
    },
    {
      "id": "bw11-1",
      "name": "tangela"
    },
    {
      "id": "pop3-1",
      "name": "blastoise"
    },
    {
      "id": "dp4-1",
      "name": "blaziken"
    },
    {
      "id": "bw5-1",
      "name": "bulbasaur"
    },
    {
      "id": "dpp-dp01",
      "name": "turtwig"
    },
    {
      "id": "swsh1-1",
      "name": "celebi v"
    },
    {
      "id": "base6-1",
      "name": "alakazam"
    },
    {
      "id": "pop9-1",
      "name": "garchomp"
    },
    {
      "id": "mcd19-4",
      "name": "alolan sandshrew"
    },
    {
      "id": "sm115-3",
      "name": "butterfree"
    },
    {
      "id": "base3-4",
      "name": "dragonite"
    },
    {
      "id": "det1-4",
      "name": "charmander"
    },
    {
      "id": "pop4-2",
      "name": "deoxys δ"
    },
    {
      "id": "ex12-4",
      "name": "delcatty"
    },
    {
      "id": "ex3-4",
      "name": "flygon"
    },
    {
      "id": "xy2-4",
      "name": "pineco"
    },
    {
      "id": "ex11-4",
      "name": "espeon δ"
    },
    {
      "id": "gym2-3",
      "name": "brock's ninetales"
    },
    {
      "id": "pop1-2",
      "name": "metagross"
    },
    {
      "id": "pl4-2",
      "name": "froslass"
    },
    {
      "id": "sm3-2",
      "name": "metapod"
    },
    {
      "id": "bw10-3",
      "name": "lileep"
    },
    {
      "id": "hgss4-4",
      "name": "drapion"
    },
    {
      "id": "ex13-3",
      "name": "deoxys δ"
    },
    {
      "id": "bw6-1",
      "name": "hoppip"
    },
    {
      "id": "xy11-4",
      "name": "skiploom"
    },
    {
      "id": "hgss4-5",
      "name": "mamoswine"
    },
    {
      "id": "sm5-3",
      "name": "yanmega"
    },
    {
      "id": "pl3-4",
      "name": "electivire fb"
    },
    {
      "id": "swsh4-2",
      "name": "kakuna"
    },
    {
      "id": "gym2-4",
      "name": "erika's venusaur"
    },
    {
      "id": "pop3-3",
      "name": "jolteon"
    },
    {
      "id": "base6-3",
      "name": "charizard"
    },
    {
      "id": "bw4-3",
      "name": "kricketot"
    },
    {
      "id": "hgss2-2",
      "name": "magmortar"
    },
    {
      "id": "swsh4-1",
      "name": "weedle"
    },
    {
      "id": "pop1-1",
      "name": "blaziken"
    },
    {
      "id": "bw8-1",
      "name": "turtwig"
    },
    {
      "id": "neo4-1",
      "name": "dark ampharos"
    },
    {
      "id": "pop7-3",
      "name": "latias"
    },
    {
      "id": "hgss1-4",
      "name": "gyarados"
    },
    {
      "id": "xy1-2",
      "name": "m venusaur-ex"
    },
    {
      "id": "ex8-2",
      "name": "beautifly"
    },
    {
      "id": "dpp-dp02",
      "name": "chimchar"
    },
    {
      "id": "col1-3",
      "name": "dialga"
    },
    {
      "id": "bw11-2",
      "name": "tangrowth"
    },
    {
      "id": "ecard2-h4",
      "name": "azumarill"
    },
    {
      "id": "neo4-2",
      "name": "dark crobat"
    },
    {
      "id": "base6-2",
      "name": "articuno"
    },
    {
      "id": "si1-3",
      "name": "onix"
    },
    {
      "id": "base4-4",
      "name": "charizard"
    },
    {
      "id": "bw8-2",
      "name": "grotle"
    },
    {
      "id": "xy7-3",
      "name": "vileplume"
    },
    {
      "id": "sm75-1",
      "name": "charmander"
    },
    {
      "id": "ex7-4",
      "name": "dark electrode"
    },
    {
      "id": "swsh1-3",
      "name": "roselia"
    },
    {
      "id": "xy5-4",
      "name": "tangela"
    },
    {
      "id": "ex11-5",
      "name": "flareon δ"
    },
    {
      "id": "base3-5",
      "name": "gengar"
    },
    {
      "id": "ex10-2",
      "name": "ariados"
    },
    {
      "id": "xy7-4",
      "name": "bellossom"
    },
    {
      "id": "pl1-5",
      "name": "dialga"
    },
    {
      "id": "basep-2",
      "name": "electabuzz"
    },
    {
      "id": "hgss2-1",
      "name": "jirachi"
    },
    {
      "id": "basep-1",
      "name": "pikachu"
    },
    {
      "id": "pop4-1",
      "name": "chimecho δ"
    },
    {
      "id": "pl4-1",
      "name": "charizard"
    },
    {
      "id": "ex9-3",
      "name": "exploud"
    },
    {
      "id": "pop6-4",
      "name": "pachirisu"
    },
    {
      "id": "ex4-2",
      "name": "team aqua's crawdaunt"
    },
    {
      "id": "xy4-2",
      "name": "venomoth"
    },
    {
      "id": "pl1-4",
      "name": "delcatty"
    },
    {
      "id": "swsh35-3",
      "name": "kakuna"
    },
    {
      "id": "base5-2",
      "name": "dark arbok"
    },
    {
      "id": "pop5-2",
      "name": "lugia"
    },
    {
      "id": "dp4-2",
      "name": "cresselia"
    },
    {
      "id": "pop3-2",
      "name": "flareon"
    },
    {
      "id": "pop9-2",
      "name": "manaphy"
    },
    {
      "id": "sm5-2",
      "name": "yanma"
    },
    {
      "id": "bw5-3",
      "name": "venusaur"
    },
    {
      "id": "ex12-5",
      "name": "gengar"
    },
    {
      "id": "pl4-3",
      "name": "heatran"
    },
    {
      "id": "bw10-4",
      "name": "cradily"
    },
    {
      "id": "pop4-3",
      "name": "flygon"
    },
    {
      "id": "ex9-4",
      "name": "gardevoir"
    },
    {
      "id": "dp4-3",
      "name": "darkrai"
    },
    {
      "id": "ecard2-h5",
      "name": "bellossom"
    },
    {
      "id": "pop1-3",
      "name": "rayquaza"
    },
    {
      "id": "xy4-3",
      "name": "yanma"
    },
    {
      "id": "bw11-3",
      "name": "shuckle"
    },
    {
      "id": "pop7-4",
      "name": "latios"
    },
    {
      "id": "xy1-1",
      "name": "venusaur-ex"
    },
    {
      "id": "neo3-1",
      "name": "ampharos"
    },
    {
      "id": "bw5-2",
      "name": "ivysaur"
    },
    {
      "id": "sm2-2",
      "name": "weepinbell"
    },
    {
      "id": "bw7-2",
      "name": "gloom"
    },
    {
      "id": "dv1-4",
      "name": "dragonair"
    },
    {
      "id": "dp1-2",
      "name": "dusknoir"
    },
    {
      "id": "dp3-4",
      "name": "entei"
    },
    {
      "id": "xy11-3",
      "name": "hoppip"
    },
    {
      "id": "swsh1-2",
      "name": "roselia"
    },
    {
      "id": "bw4-2",
      "name": "seedot"
    },
    {
      "id": "sm9-4",
      "name": "kakuna"
    },
    {
      "id": "ex10-1",
      "name": "ampharos"
    },
    {
      "id": "si1-4",
      "name": "togepi"
    },
    {
      "id": "dp1-3",
      "name": "electivire"
    },
    {
      "id": "sm12-3",
      "name": "gloom"
    },
    {
      "id": "hgss1-5",
      "name": "hitmontop"
    },
    {
      "id": "ex3-5",
      "name": "golem"
    },
    {
      "id": "ex4-3",
      "name": "team aqua's kyogre"
    },
    {
      "id": "dv1-5",
      "name": "dragonite"
    },
    {
      "id": "dp3-5",
      "name": "flygon"
    },
    {
      "id": "bw1-3",
      "name": "servine"
    },
    {
      "id": "ex8-3",
      "name": "breloom"
    },
    {
      "id": "neo3-2",
      "name": "blissey"
    },
    {
      "id": "neo4-3",
      "name": "dark donphan"
    },
    {
      "id": "bw7-3",
      "name": "vileplume"
    },
    {
      "id": "dpp-dp03",
      "name": "piplup"
    },
    {
      "id": "sm115-4",
      "name": "paras"
    },
    {
      "id": "xy2-5",
      "name": "seedot"
    },
    {
      "id": "ex14-2",
      "name": "blastoise δ"
    },
    {
      "id": "det1-5",
      "name": "charizard"
    },
    {
      "id": "pl1-6",
      "name": "dialga"
    },
    {
      "id": "dpp-dp04",
      "name": "pachirisu"
    },
    {
      "id": "xy5-5",
      "name": "tangrowth"
    },
    {
      "id": "xy2-6",
      "name": "nuzleaf"
    },
    {
      "id": "ex14-3",
      "name": "camerupt"
    },
    {
      "id": "base5-3",
      "name": "dark blastoise"
    },
    {
      "id": "neo4-4",
      "name": "dark espeon"
    },
    {
      "id": "hgss4-6",
      "name": "nidoking"
    },
    {
      "id": "bw8-3",
      "name": "torterra"
    },
    {
      "id": "sm75-3",
      "name": "charizard"
    },
    {
      "id": "xy11-5",
      "name": "jumpluff"
    },
    {
      "id": "det1-6",
      "name": "arcanine"
    },
    {
      "id": "bw9-2",
      "name": "kakuna"
    },
    {
      "id": "pop3-4",
      "name": "minun"
    },
    {
      "id": "bw4-4",
      "name": "kricketune"
    },
    {
      "id": "hgss1-6",
      "name": "jumpluff"
    },
    {
      "id": "sm12-4",
      "name": "vileplume-gx"
    },
    {
      "id": "xy5-6",
      "name": "treecko"
    },
    {
      "id": "mcd19-7",
      "name": "gastly"
    },
    {
      "id": "gym2-5",
      "name": "giovanni's gyarados"
    },
    {
      "id": "base4-5",
      "name": "clefable"
    }
  ],
  "page": 1,
  "pagesize": 250,
  "count": 250,
  "totalcount": 16125
}
